techtonique_apis/__init__.py
techtonique_apis/config.py
techtonique_apis/techto_forecast.py
techtonique_apis/techto_ml.py
techtonique_apis/techto_reserving.py
techtonique_apis/techto_simulation.py
techtonique_apis/techto_survival.py
techtonique_apis/techtonique_apis.py
techtonique_apis-0.8.4.dist-info/licenses/LICENSE
techtonique_apis-0.8.4.dist-info/METADATA
techtonique_apis-0.8.4.dist-info/WHEEL
techtonique_apis-0.8.4.dist-info/top_level.txt
techtonique_apis-0.8.4.dist-info/RECORD
