Metadata-Version: 2.4
Name: techtonique_apis
Version: 0.8.4
Summary: Tools for interacting with Techtonique API
Home-page: https://github.com/Techtonique/techtonique-apis
Author: T. Moudiki
Author-email: thierry.moudiki@gmail.com
License: MIT license
Keywords: Techtonique,api
Classifier: Development Status :: 2 - Pre-Alpha
Classifier: Intended Audience :: Developers
Classifier: License :: OSI Approved :: MIT License
Classifier: Natural Language :: English
Classifier: Programming Language :: Python :: 3
Classifier: Programming Language :: Python :: 3.6
Classifier: Programming Language :: Python :: 3.7
Classifier: Programming Language :: Python :: 3.8
Requires-Python: >=3.6
License-File: LICENSE
Requires-Dist: certifi
Requires-Dist: charset-normalizer
Requires-Dist: idna
Requires-Dist: pandas
Requires-Dist: requests
Requires-Dist: urllib3
Requires-Dist: matplotlib
Requires-Dist: python-dotenv
Requires-Dist: xlwings
Dynamic: author
Dynamic: author-email
Dynamic: classifier
Dynamic: description
Dynamic: home-page
Dynamic: keywords
Dynamic: license
Dynamic: license-file
Dynamic: requires-dist
Dynamic: requires-python
Dynamic: summary
